{
  "timestamp": 1754622989080,
  "summary": {
    "uptime": {
      "milliseconds": 120015,
      "hours": 0.0333375,
      "formatted": "2m 0s"
    },
    "requests": {
      "total": 0,
      "successful": 0,
      "failed": 0,
      "successRate": 0,
      "averageResponseTime": 0,
      "requestsPerHour": 0
    },
    "routing": {
      "total": 0,
      "successful": 0,
      "fallback": 0,
      "errors": 0,
      "successRate": 0,
      "averageRoutingTime": 0
    },
    "classification": {
      "total": 0,
      "accurate": 0,
      "accuracy": 0,
      "averageConfidence": 0
    },
    "models": [],
    "system": {
      "memoryUsage": 67.90325927734375,
      "cpuUsage": 0,
      "peakMemoryUsage": 67.90166473388672,
      "requestsPerMinute": 0
    }
  },
  "detailed": {
    "system": {
      "startTime": 1754622869065,
      "totalRequests": 0,
      "successfulRequests": 0,
      "failedRequests": 0,
      "averageResponseTime": 0,
      "peakMemoryUsage": 71200056,
      "peakCpuUsage": 0
    },
    "models": {},
    "routing": {
      "totalRoutes": 0,
      "successfulRoutes": 0,
      "fallbackRoutes": 0,
      "routingErrors": 0,
      "subjectDistribution": {},
      "averageRoutingTime": 0
    },
    "classification": {
      "totalClassifications": 0,
      "accurateClassifications": 0,
      "averageConfidence": 0,
      "subjectAccuracy": {}
    },
    "performance": {
      "responseTimeHistory": [],
      "memoryUsageHistory": [
        {
          "timestamp": 1754622929074,
          "heapUsed": 48252392,
          "heapTotal": 51175424,
          "external": 22362993,
          "rss": 93061120
        },
        {
          "timestamp": 1754622989080,
          "heapUsed": 71200056,
          "heapTotal": 98082816,
          "external": 23066369,
          "rss": 142659584
        }
      ],
      "cpuUsageHistory": [
        {
          "timestamp": 1754622929074,
          "user": 812000,
          "system": 390000
        },
        {
          "timestamp": 1754622989080,
          "user": 1093000,
          "system": 390000
        }
      ],
      "errorRateHistory": []
    },
    "realtime": {
      "currentRequests": 0,
      "requestsPerMinute": 0,
      "averageResponseTime": 0,
      "errorRate": 0,
      "memoryUsage": 67.90325927734375,
      "cpuUsage": 0
    },
    "uptime": 120015,
    "timestamp": 1754622989080
  }
}