{
  "timestamp": 1754844471862,
  "summary": {
    "uptime": {
      "milliseconds": 1080175,
      "hours": 0.3000486111111111,
      "formatted": "18m 0s"
    },
    "requests": {
      "total": 0,
      "successful": 0,
      "failed": 0,
      "successRate": 0,
      "averageResponseTime": 0,
      "requestsPerHour": 0
    },
    "routing": {
      "total": 0,
      "successful": 0,
      "fallback": 0,
      "errors": 0,
      "successRate": 0,
      "averageRoutingTime": 0
    },
    "classification": {
      "total": 0,
      "accurate": 0,
      "accuracy": 0,
      "averageConfidence": 0
    },
    "models": [],
    "system": {
      "memoryUsage": 28.77509307861328,
      "cpuUsage": 0,
      "peakMemoryUsage": 28.77190399169922,
      "requestsPerMinute": 0
    }
  },
  "detailed": {
    "system": {
      "startTime": 1754843391687,
      "totalRequests": 0,
      "successfulRequests": 0,
      "failedRequests": 0,
      "averageResponseTime": 0,
      "peakMemoryUsage": 30169528,
      "peakCpuUsage": 0
    },
    "models": {},
    "routing": {
      "totalRoutes": 0,
      "successfulRoutes": 0,
      "fallbackRoutes": 0,
      "routingErrors": 0,
      "subjectDistribution": {},
      "averageRoutingTime": 0
    },
    "classification": {
      "totalClassifications": 0,
      "accurateClassifications": 0,
      "averageConfidence": 0,
      "subjectAccuracy": {}
    },
    "performance": {
      "responseTimeHistory": [],
      "memoryUsageHistory": [
        {
          "timestamp": 1754843451701,
          "heapUsed": 29487344,
          "heapTotal": 32870400,
          "external": 21807791,
          "rss": 73011200
        },
        {
          "timestamp": 1754843511707,
          "heapUsed": 29554848,
          "heapTotal": 32870400,
          "external": 21808207,
          "rss": 73162752
        },
        {
          "timestamp": 1754843571714,
          "heapUsed": 29585960,
          "heapTotal": 32870400,
          "external": 21816799,
          "rss": 73187328
        },
        {
          "timestamp": 1754843631719,
          "heapUsed": 29617424,
          "heapTotal": 32870400,
          "external": 21817199,
          "rss": 73211904
        },
        {
          "timestamp": 1754843691737,
          "heapUsed": 29649464,
          "heapTotal": 32870400,
          "external": 21817599,
          "rss": 73281536
        },
        {
          "timestamp": 1754843751748,
          "heapUsed": 29682352,
          "heapTotal": 32870400,
          "external": 21826191,
          "rss": 73314304
        },
        {
          "timestamp": 1754843811754,
          "heapUsed": 29723312,
          "heapTotal": 32870400,
          "external": 21826591,
          "rss": 73318400
        },
        {
          "timestamp": 1754843871768,
          "heapUsed": 29756544,
          "heapTotal": 32870400,
          "external": 21835183,
          "rss": 73351168
        },
        {
          "timestamp": 1754843931778,
          "heapUsed": 29790056,
          "heapTotal": 32870400,
          "external": 21839764,
          "rss": 73383936
        },
        {
          "timestamp": 1754843991793,
          "heapUsed": 29867904,
          "heapTotal": 32870400,
          "external": 21844646,
          "rss": 73478144
        },
        {
          "timestamp": 1754844051802,
          "heapUsed": 29905288,
          "heapTotal": 32870400,
          "external": 21849819,
          "rss": 73515008
        },
        {
          "timestamp": 1754844111830,
          "heapUsed": 29941816,
          "heapTotal": 32870400,
          "external": 21855291,
          "rss": 73535488
        },
        {
          "timestamp": 1754844171832,
          "heapUsed": 29977416,
          "heapTotal": 32870400,
          "external": 21861046,
          "rss": 73572352
        },
        {
          "timestamp": 1754844231845,
          "heapUsed": 30020376,
          "heapTotal": 32870400,
          "external": 21867108,
          "rss": 73621504
        },
        {
          "timestamp": 1754844291850,
          "heapUsed": 30056888,
          "heapTotal": 32870400,
          "external": 21873464,
          "rss": 73666560
        },
        {
          "timestamp": 1754844351854,
          "heapUsed": 30094320,
          "heapTotal": 32870400,
          "external": 21880113,
          "rss": 73707520
        },
        {
          "timestamp": 1754844411858,
          "heapUsed": 30131696,
          "heapTotal": 32870400,
          "external": 21887061,
          "rss": 73748480
        },
        {
          "timestamp": 1754844471862,
          "heapUsed": 30169528,
          "heapTotal": 32870400,
          "external": 21894304,
          "rss": 73793536
        }
      ],
      "cpuUsageHistory": [
        {
          "timestamp": 1754843451701,
          "user": 1796000,
          "system": 765000
        },
        {
          "timestamp": 1754843511707,
          "user": 1796000,
          "system": 781000
        },
        {
          "timestamp": 1754843571714,
          "user": 1796000,
          "system": 781000
        },
        {
          "timestamp": 1754843631719,
          "user": 1812000,
          "system": 781000
        },
        {
          "timestamp": 1754843691737,
          "user": 1812000,
          "system": 781000
        },
        {
          "timestamp": 1754843751748,
          "user": 1812000,
          "system": 781000
        },
        {
          "timestamp": 1754843811754,
          "user": 1812000,
          "system": 781000
        },
        {
          "timestamp": 1754843871768,
          "user": 1812000,
          "system": 781000
        },
        {
          "timestamp": 1754843931778,
          "user": 1812000,
          "system": 781000
        },
        {
          "timestamp": 1754843991793,
          "user": 1828000,
          "system": 781000
        },
        {
          "timestamp": 1754844051802,
          "user": 1828000,
          "system": 781000
        },
        {
          "timestamp": 1754844111830,
          "user": 1828000,
          "system": 781000
        },
        {
          "timestamp": 1754844171832,
          "user": 1828000,
          "system": 781000
        },
        {
          "timestamp": 1754844231845,
          "user": 1828000,
          "system": 781000
        },
        {
          "timestamp": 1754844291850,
          "user": 1828000,
          "system": 781000
        },
        {
          "timestamp": 1754844351854,
          "user": 1843000,
          "system": 781000
        },
        {
          "timestamp": 1754844411858,
          "user": 1843000,
          "system": 781000
        },
        {
          "timestamp": 1754844471862,
          "user": 1843000,
          "system": 781000
        }
      ],
      "errorRateHistory": []
    },
    "realtime": {
      "currentRequests": 0,
      "requestsPerMinute": 0,
      "averageResponseTime": 0,
      "errorRate": 0,
      "memoryUsage": 28.77509307861328,
      "cpuUsage": 0
    },
    "uptime": 1080175,
    "timestamp": 1754844471862
  }
}