{
  "summary": "Based on the provided search results, it's clear that \"hi\" is a common greeting. The search results consist of dictionary definitions from Cambridge Dictionary, Merriam-Webster, Dictionary.com, YourDictionary, and US Dictionary. While the descriptions for each result are missing, the fact that these reputable dictionaries all have entries for \"hi\" strongly suggests its widespread use and acceptance as an informal greeting.\n\nTherefore, the answer to the query \"hi\" is:\n\n**\"Hi\" is a common, informal greeting.**\n\n**Limitations and Uncertainties:**\n\n*   **Lack of Description:** The provided search results are limited by the absence of descriptions. We can only infer the meaning based on the titles indicating dictionary entries.\n*   **Context:** Without the dictionary definitions themselves, we cannot provide a more nuanced explanation of its usage, such as appropriate contexts (e.g., informal situations) or potential variations (e.g., \"hi there\").\n\n**Further Information (based on general knowledge):**\n\nWhile not explicitly stated in the search results, it's common knowledge that \"hi\" is:\n\n*   **Informal:** It's generally used in casual settings with friends, family, or acquaintances.\n*   **Versatile:** It can be used to initiate a conversation or simply acknowledge someone's presence.\n*   **Interchangeable with other greetings:** It's often used interchangeably with other informal greetings like \"hello,\" \"hey,\" or \"howdy.\"\n\n**In conclusion, although the provided search results are minimal, they confirm that \"hi\" is a recognized and commonly used greeting in the English language.**",
  "sources": [
    {
      "title": "HI | English meaning - Cambridge Dictionary",
      "url": ""
    },
    {
      "title": "HI Definition &amp; Meaning - Merriam-Webster",
      "url": ""
    },
    {
      "title": "HI Definition &amp; Meaning | Dictionary.com",
      "url": ""
    },
    {
      "title": "Hi Definition &amp; Meaning | YourDictionary",
      "url": ""
    },
    {
      "title": "Hi: Definition, Meaning, and Examples - US Dictionary",
      "url": ""
    }
  ],
  "aiGenerated": true,
  "rawResults": [
    {
      "title": "HI | English meaning - Cambridge Dictionary",
      "snippet": "No description available",
      "url": "",
      "raw": {
        "title": "HI | English meaning - Cambridge Dictionary",
        "snippet": "No description available",
        "url": ""
      },
      "score": 11
    },
    {
      "title": "HI Definition &amp; Meaning - Merriam-Webster",
      "snippet": "No description available",
      "url": "",
      "raw": {
        "title": "HI Definition &amp; Meaning - Merriam-Webster",
        "snippet": "No description available",
        "url": ""
      },
      "score": 11.4
    },
    {
      "title": "HI Definition &amp; Meaning | Dictionary.com",
      "snippet": "No description available",
      "url": "",
      "raw": {
        "title": "HI Definition &amp; Meaning | Dictionary.com",
        "snippet": "No description available",
        "url": ""
      },
      "score": 11.200000000000001
    },
    {
      "title": "Hi Definition &amp; Meaning | YourDictionary",
      "snippet": "No description available",
      "url": "",
      "raw": {
        "title": "Hi Definition &amp; Meaning | YourDictionary",
        "snippet": "No description available",
        "url": ""
      },
      "score": 11.200000000000001
    },
    {
      "title": "Hi: Definition, Meaning, and Examples - US Dictionary",
      "snippet": "No description available",
      "url": "",
      "raw": {
        "title": "Hi: Definition, Meaning, and Examples - US Dictionary",
        "snippet": "No description available",
        "url": ""
      },
      "score": 13.000000000000002
    }
  ],
  "query": "hi",
  "timestamp": "2025-07-02T07:10:19.715Z",
  "userId": "6864dadd6acee90939b1f4c8"
}